fastapi_contrib/__init__.py
fastapi_contrib/conf.py
fastapi_contrib/exception_handlers.py
fastapi_contrib/exceptions.py
fastapi_contrib/pagination.py
fastapi_contrib/permissions.py
fastapi_contrib/routes.py
fastapi_contrib/auth/__init__.py
fastapi_contrib/auth/backends.py
fastapi_contrib/auth/middlewares.py
fastapi_contrib/auth/models.py
fastapi_contrib/auth/permissions.py
fastapi_contrib/auth/serializers.py
fastapi_contrib/auth/utils.py
fastapi_contrib/common/__init__.py
fastapi_contrib/common/middlewares.py
fastapi_contrib/common/responses.py
fastapi_contrib/common/utils.py
fastapi_contrib/db/__init__.py
fastapi_contrib/db/client.py
fastapi_contrib/db/models.py
fastapi_contrib/db/utils.py
fastapi_contrib/serializers/__init__.py
fastapi_contrib/serializers/common.py
fastapi_contrib/serializers/openapi.py
fastapi_contrib/serializers/utils.py
fastapi_contrib/tracing/__init__.py
fastapi_contrib/tracing/middlewares.py
fastapi_contrib/tracing/utils.py
fastapi_contrib-0.2.10.dist-info/AUTHORS.rst
fastapi_contrib-0.2.10.dist-info/LICENSE
fastapi_contrib-0.2.10.dist-info/METADATA
fastapi_contrib-0.2.10.dist-info/WHEEL
fastapi_contrib-0.2.10.dist-info/top_level.txt
fastapi_contrib-0.2.10.dist-info/RECORD
