Metadata-Version: 2.1
Name: fastapi-contrib
Version: 0.2.10
Summary: Opinionated set of utilities on top of FastAPI
Home-page: https://github.com/identixone/fastapi_contrib
Author: Lev Rubel
Author-email: l@datacorp.ee
License: MIT license
Keywords: fastapi_contrib
Platform: UNKNOWN
Classifier: Development Status :: 2 - Pre-Alpha
Classifier: Intended Audience :: Developers
Classifier: License :: OSI Approved :: MIT License
Classifier: Natural Language :: English
Classifier: Programming Language :: Python :: 3
Classifier: Programming Language :: Python :: 3.7
Classifier: Programming Language :: Python :: 3.8
Classifier: Programming Language :: Python :: 3.9
Requires-Dist: fastapi (>=0.63.0)
Provides-Extra: all
Requires-Dist: motor (>=2.0.0) ; extra == 'all'
Requires-Dist: ujson (<2.0.0) ; extra == 'all'
Requires-Dist: pytz ; extra == 'all'
Requires-Dist: jaeger-client (>=4.1.0) ; extra == 'all'
Requires-Dist: opentracing (>=2.2.0) ; extra == 'all'
Provides-Extra: jaegertracing
Requires-Dist: jaeger-client (>=4.1.0) ; extra == 'jaegertracing'
Requires-Dist: opentracing (>=2.2.0) ; extra == 'jaegertracing'
Provides-Extra: mongo
Requires-Dist: motor (>=2.0.0) ; extra == 'mongo'
Provides-Extra: pytz
Requires-Dist: pytz ; extra == 'pytz'
Provides-Extra: ujson
Requires-Dist: ujson (<2.0.0) ; extra == 'ujson'
